rtl_dev/main_top.v
`timescale 1ns / 1ps

// main_top.v - Main module for the system

module main_top (
  input CLK8,
 
  input BG_I,
  input BG_MB,
 
  input RESET_I,
  input RESET_MB,

  inout BR_MB,
  inout BGACK_MB,
  inout HALT_MB,

  output CLK8_O,
  output HALT_I,
  output BR_I,
  output BGACK_I
);

  reg [3:0] state = 4'd0;

  reg halt_i_int = 1'bz;
  reg halt_mb_int = 1'bz;
  reg br_i_int = 1'bz;
  reg br_mb_int = 1'bz;
  reg bgack_i_int = 1'bz;
  reg bgack_mb_int = 1'bz;


  // Internal logic for state machine or control generation
  always @(posedge CLK8 or negedge RESET_MB) begin  
    if( !RESET_MB ) begin
      halt_i_int <= HALT_MB;
      halt_mb_int <= 1'bz;
      br_i_int <= 1'b0;
      br_mb_int <= 1'bz;
      bgack_i_int <= 1'b0;
      bgack_mb_int <= 1'bz;

      state <= 'd0; // Reset state
    end
    else begin
      case(state)
        4'd0: begin // BUS NOT OURS
          halt_i_int <= 1'bz;
          halt_mb_int <= 1'b0;
          br_i_int <= 1'b0;
          br_mb_int <= 1'bz;
          bgack_i_int <= 1'b0;
          bgack_mb_int <= 1'bz;

          if( BR_MB && BGACK_MB && BG_MB ) begin
            state <= 4'd1; // If no bus arb in play, move to request state
          end
        end
      
        4'd1: begin // START REQUEST, WAIT BG
          halt_i_int <= 1'bz;
          halt_mb_int <= 1'b0;
          br_i_int <= 1'b0;
          br_mb_int <= 1'b0;
          bgack_i_int <= 1'b0;
          bgack_mb_int <= 1'bz;

          if( !BG_MB && BGACK_MB ) begin
            state <= 4'd2; // If bus grant, move to accept state
          end
        end
        4'd2: begin // BUS IS MINE, AWAIT BR
          halt_i_int <= 1'bz;
          halt_mb_int <= 1'b0;
          br_i_int <= 1'b1;
          br_mb_int <= 1'bz;
          bgack_i_int <= 1'b1;
          bgack_mb_int <= 1'b0;

          if( !BR_MB ) begin
            state <= 4'd3; // If bus request received, move to relinquish state
          end
        end
        4'd3: begin // BR RECEIVED, PASS THROUGH AND AWAIT BGI, WHILST STILL HOLDING BUS
          halt_i_int <= 1'bz;
          halt_mb_int <= 1'b0;
          br_i_int <= 1'b0;
          br_mb_int <= 1'bz;
          bgack_i_int <= 1'b1;
          bgack_mb_int <= 1'b0;

          if( !BG_I ) begin
            state <= 4'd4; // If another request comes in move to relinquish
          end
        end
        4'd4: begin // RELINQUISH, AWAIT BG_MB
          halt_i_int <= 1'bz;
          halt_mb_int <= 1'b0;
          br_i_int <= 1'b0;
          br_mb_int <= 1'bz;
          bgack_i_int <= 1'b0;
          bgack_mb_int <= 1'bz;

          if( !BG_MB ) begin
            state <= 4'd0; // Back to initial state
          end
        end
        default: begin
          state <= 4'd0; // Default back to initial state
        end
      endcase
    end
//    state <= state + 'h1;
  end

  assign CLK8_O = CLK8;

  assign HALT_I = ( RESET_MB ? ( ( halt_i_int == 1'bz ) ? 1'bz : halt_i_int ) : HALT_MB );
  assign HALT_MB = ( RESET_MB ? ( ( halt_mb_int == 1'bz ) ? 1'bz : halt_mb_int ) : 1'bz );
  assign BR_I = ( br_i_int == 1'bz ) ? 1'bz : br_i_int;
  assign BR_MB = ( br_mb_int == 1'bz ) ? 1'bz : br_mb_int;
  assign BGACK_I = ( bgack_i_int == 1'bz ) ? 1'bz : bgack_i_int;
  assign BGACK_MB = ( bgack_mb_int == 1'bz ) ? 1'bz : bgack_mb_int;

endmodule

rtl_dev/test.v
module test;

	// regs
  reg CLK8;

  reg RESET_I;
  reg RESET_MB;
  
  reg BG_I;
  reg BG_MB;
 
	// Outputs
	wire CLK8_O;

  wire HALT_I;
  pullup( HALT_I );

  wire BR_I;
  wire BGACK_I;

// inout
  wire BR_MB;
  pullup( BR_MB );
  reg BR_MB_val;
  reg BR_MB_en;
  assign BR_MB = BR_MB_en ? BR_MB_val : 1'bz;
  wire BR_MB_read = BR_MB_en ? BR_MB_val : BR_MB;

  wire BGACK_MB;
  pullup( BGACK_MB );
  reg BGACK_MB_val;
  reg BGACK_MB_en;
  assign BGACK_MB = BGACK_MB_en ? BGACK_MB_val : 1'bz;
  wire BGACK_MB_read = BGACK_MB_en ? BGACK_MB_val : BGACK_MB;

  wire HALT_MB;  
  pullup( HALT_MB );
  reg HALT_MB_val;
  reg HALT_MB_en;
  assign HALT_MB = HALT_MB_en ? HALT_MB_val : 1'bz;
  wire HALT_MB_read = HALT_MB_en ? HALT_MB_val : HALT_MB;


	// Instantiate the Unit Under Test (UUT)
	main_top uut (
    .CLK8(CLK8),
    .CLK8_O(CLK8_O),

    .RESET_I(RESET_I),
    .RESET_MB(RESET_MB),

    .HALT_I(HALT_I),
    .HALT_MB(HALT_MB),

    .BR_I(BR_I),
    .BR_MB(BR_MB),

    .BG_I(BG_I),
    .BG_MB(BG_MB),

    .BGACK_I(BGACK_I),
    .BGACK_MB(BGACK_MB)
	);

	initial begin
		$dumpfile("wave.vcd");
		$dumpvars(0, uut);
	 
		// Initialize Inputs
		CLK8 = 0;
    RESET_I = 0;
		RESET_MB = 0;

    BR_MB_val = 1'bz;
    BR_MB_en = 1'b0;

    BGACK_MB_val = 1'b0;
    BGACK_MB_en = 1'b0;

    HALT_MB_val = 1'b0;
    HALT_MB_en = 1'b1;
  
    BG_I = 1;
    BG_MB = 1;
  //    BGACK_I = 0;
  //    BGACK_MB = 0;

		// Wait 100 ns for global reset to finish
		#100;
		// Add stimulus here
    RESET_MB = 1;
    RESET_I = 1;
    HALT_MB_en = 1'b0;

    #400;
    BG_MB = 0;

    #400;
    BG_MB = 1;

    #900;
    BR_MB_val = 1'b0;
    BR_MB_en = 1'b1;

    #400;
    BG_I = 0;
    #350;
    BG_MB = 0;

    #100;
    BGACK_MB_en = 1'b1;
    BR_MB_en = 1'b0;

    #125;
    BG_MB = 1;

    #1250;
    BGACK_MB_en  = 1'b0;
    #400;
    BG_MB = 0;

    #400;
    BG_MB = 1;

    #450;
    RESET_MB = 0;
    HALT_MB_en = 1'b1;
    HALT_MB_val = 1'b0;

    #600;
    RESET_MB = 1;
    HALT_MB_en = 1'b0;

	end

//	initial #447 SWITCH=0;
	
	initial #7000 $finish;


	always #62 CLK8 = ~CLK8;

      
endmodule

rtl_dev/wave.vcd
$date
	Tue Sep 22 14:25:15 2026
$end
$version
	Icarus Verilog
$end
$timescale
	1ps
$end
$scope module test $end
$scope module uut $end
$var wire 1 ! BGACK_MB $end
$var wire 1 " BG_I $end
$var wire 1 # BG_MB $end
$var wire 1 $ BR_MB $end
$var wire 1 % CLK8 $end
$var wire 1 & CLK8_O $end
$var wire 1 ' HALT_I $end
$var wire 1 ( HALT_MB $end
$var wire 1 ) RESET_I $end
$var wire 1 * RESET_MB $end
$var wire 1 + BR_I $end
$var wire 1 , BGACK_I $end
$var reg 1 - bgack_i_int $end
$var reg 1 . bgack_mb_int $end
$var reg 1 / br_i_int $end
$var reg 1 0 br_mb_int $end
$var reg 1 1 halt_i_int $end
$var reg 1 2 halt_mb_int $end
$var reg 4 3 state [3:0] $end
$upscope $end
$upscope $end
$enddefinitions $end
$comment Show the parameter values. $end
$dumpall
$end
#0
$dumpvars
b0 3
z2
x1
z0
0/
z.
0-
x,
x+
0*
0)
0(
0'
0&
0%
1$
1#
1"
1!
$end
#62000
01
1&
1%
#100000
1(
x'
1)
1*
#124000
0&
0%
#186000
x(
1'
b1 3
02
z1
1&
1%
#248000
0&
0%
#310000
x$
00
1&
1%
#372000
0&
0%
#434000
1&
1%
#496000
0&
0%
#500000
0#
#558000
b10 3
1&
1%
#620000
0&
0%
#682000
x!
1$
0.
1-
z0
1/
1&
1%
#744000
0&
0%
#806000
1&
1%
#868000
0&
0%
#900000
1#
#930000
1&
1%
#992000
0&
0%
#1054000
1&
1%
#1116000
0&
0%
#1178000
1&
1%
#1240000
0&
0%
#1302000
1&
1%
#1364000
0&
0%
#1426000
1&
1%
#1488000
0&
0%
#1550000
1&
1%
#1612000
0&
0%
#1674000
1&
1%
#1736000
0&
0%
#1798000
1&
1%
#1800000
0$
#1860000
0&
0%
#1922000
b11 3
1&
1%
#1984000
0&
0%
#2046000
0/
1&
1%
#2108000
0&
0%
#2170000
1&
1%
#2200000
0"
#2232000
0&
0%
#2294000
b100 3
1&
1%
#2356000
0&
0%
#2418000
1!
z.
0-
1&
1%
#2480000
0&
0%
#2542000
1&
1%
#2550000
0#
#2604000
0&
0%
#2650000
1$
0!
#2666000
b0 3
1&
1%
#2728000
0&
0%
#2775000
1#
#2790000
1&
1%
#2852000
0&
0%
#2914000
1&
1%
#2976000
0&
0%
#3038000
1&
1%
#3100000
0&
0%
#3162000
1&
1%
#3224000
0&
0%
#3286000
1&
1%
#3348000
0&
0%
#3410000
1&
1%
#3472000
0&
0%
#3534000
1&
1%
#3596000
0&
0%
#3658000
1&
1%
#3720000
0&
0%
#3782000
1&
1%
#3844000
0&
0%
#3906000
1&
1%
#3968000
0&
0%
#4025000
1!
#4030000
b1 3
1&
1%
#4092000
0&
0%
#4154000
x$
00
1&
1%
#4216000
0&
0%
#4278000
1&
1%
#4340000
0&
0%
#4402000
1&
1%
#4425000
0#
#4464000
0&
0%
#4526000
b10 3
1&
1%
#4588000
0&
0%
#4650000
x!
1$
0.
1-
z0
1/
1&
1%
#4712000
0&
0%
#4774000
1&
1%
#4825000
1#
#4836000
0&
0%
#4898000
1&
1%
#4960000
0&
0%
#5022000
1&
1%
#5084000
0&
0%
#5146000
1&
1%
#5208000
0&
0%
#5270000
1&
1%
#5275000
1!
b0 3
z.
0-
0/
z2
11
0'
0(
0*
#5332000
0&
0%
#5394000
01
1&
1%
#5456000
0&
0%
#5518000
1&
1%
#5580000
0&
0%
#5642000
1&
1%
#5704000
0&
0%
#5766000
1&
1%
#5828000
0&
0%
#5875000
1(
x'
1*
#5890000
x(
1'
b1 3
02
z1
1&
1%
#5952000
0&
0%
#6014000
x$
00
1&
1%
